MANIFEST.in
README.md
setup.py
template_nest/nest.py
template_nest.egg-info/PKG-INFO
template_nest.egg-info/SOURCES.txt
template_nest.egg-info/dependency_links.txt
template_nest.egg-info/top_level.txt
template_nest/tests/prepare.py
template_nest/tests/test_bad_params.py
template_nest/tests/test_defaults.py
template_nest/tests/test_escape_with_fixed_indent.py
template_nest/tests/test_escapes.py
template_nest/tests/test_indent.py
template_nest/tests/test_methods.py
template_nest/tests/test_params.py
template_nest/tests/test_render.py
template_nest/tests/templates/escapes.html
template_nest/tests/templates/escapes_e.html
template_nest/tests/templates/nested_default_contents.html
template_nest/tests/templates/nested_default_outer.html
template_nest/tests/templates/table.html
template_nest/tests/templates/td.html
template_nest/tests/templates/tr.html
template_nest/tests/templates/tr_default.html
template_nest/tests/templates/tr_default_ns.html